{
  "binding_errors": [
    "bridge_frame_install_error: Frame.evaluate: Frame was detached",
    "bridge_frame_install_error: Frame.evaluate: Target page, context or browser has been closed",
    "pump_error: Page.evaluate: Target page, context or browser has been closed"
  ],
  "traces": [
    {
      "_trace": true,
      "kind": "bridge_init",
      "url": "about:blank",
      "ts": 1779853347064,
      "extra": {
        "isTop": true,
        "hasBinding": true
      }
    },
    {
      "_trace": true,
      "kind": "iframes_at_init",
      "url": "about:blank",
      "ts": 1779853347065,
      "extra": {
        "count": 0,
        "items": []
      }
    },
    {
      "_trace": true,
      "kind": "bridge_init",
      "url": "https://conxa.pipedrive.com/setup-guide",
      "ts": 1779853348154,
      "extra": {
        "isTop": true,
        "hasBinding": true
      }
    },
    {
      "_trace": true,
      "kind": "iframes_at_init",
      "url": "https://conxa.pipedrive.com/setup-guide",
      "ts": 1779853348157,
      "extra": {
        "count": 0,
        "items": []
      }
    },
    {
      "_trace": true,
      "kind": "bridge_init",
      "url": "about:blank",
      "ts": 1779853348697,
      "extra": {
        "isTop": false,
        "hasBinding": true
      }
    },
    {
      "_trace": true,
      "kind": "iframes_at_init",
      "url": "about:blank",
      "ts": 1779853348697,
      "extra": {
        "count": 0,
        "items": []
      }
    },
    {
      "_trace": true,
      "kind": "iframe_added",
      "url": "https://conxa.pipedrive.com/setup-guide",
      "ts": 1779853348698,
      "extra": {
        "src": "",
        "id": "",
        "testId": ""
      }
    },
    {
      "_trace": true,
      "kind": "bridge_init",
      "url": "about:blank",
      "ts": 1779853348990,
      "extra": {
        "isTop": false,
        "hasBinding": true
      }
    },
    {
      "_trace": true,
      "kind": "iframes_at_init",
      "url": "about:blank",
      "ts": 1779853348990,
      "extra": {
        "count": 0,
        "items": []
      }
    },
    {
      "_trace": true,
      "kind": "iframe_added",
      "url": "about:blank",
      "ts": 1779853349069,
      "extra": {
        "src": "",
        "id": "",
        "testId": ""
      }
    },
    {
      "_trace": true,
      "kind": "bridge_init",
      "url": "about:blank",
      "ts": 1779853350306,
      "extra": {
        "isTop": false,
        "hasBinding": true
      }
    },
    {
      "_trace": true,
      "kind": "iframes_at_init",
      "url": "about:blank",
      "ts": 1779853350306,
      "extra": {
        "count": 0,
        "items": []
      }
    },
    {
      "_trace": true,
      "kind": "iframe_added",
      "url": "https://conxa.pipedrive.com/setup-guide",
      "ts": 1779853350311,
      "extra": {
        "src": "",
        "id": "intercom-frame",
        "testId": ""
      }
    },
    {
      "_trace": true,
      "kind": "event",
      "url": "https://conxa.pipedrive.com/setup-guide",
      "ts": 1779853388202,
      "extra": {
        "t": "focusin"
      }
    },
    {
      "_trace": true,
      "kind": "event",
      "url": "https://conxa.pipedrive.com/setup-guide",
      "ts": 1779853388420,
      "extra": {
        "t": "click"
      }
    },
    {
      "_trace": true,
      "kind": "event",
      "url": "https://conxa.pipedrive.com/persons/list/user/everyone",
      "ts": 1779853390536,
      "extra": {
        "t": "focusout"
      }
    },
    {
      "_trace": true,
      "kind": "event",
      "url": "https://conxa.pipedrive.com/persons/list/user/everyone",
      "ts": 1779853390537,
      "extra": {
        "t": "focusin"
      }
    },
    {
      "_trace": true,
      "kind": "event",
      "url": "https://conxa.pipedrive.com/persons/list/user/everyone",
      "ts": 1779853390761,
      "extra": {
        "t": "click"
      }
    },
    {
      "_trace": true,
      "kind": "event",
      "url": "https://conxa.pipedrive.com/persons/list/user/everyone?quickFilter=none",
      "ts": 1779853392187,
      "extra": {
        "t": "focusout"
      }
    },
    {
      "_trace": true,
      "kind": "event",
      "url": "https://conxa.pipedrive.com/persons/list/user/everyone?quickFilter=none",
      "ts": 1779853392188,
      "extra": {
        "t": "focusin"
      }
    },
    {
      "_trace": true,
      "kind": "event",
      "url": "https://conxa.pipedrive.com/persons/list/user/everyone?quickFilter=none",
      "ts": 1779853393594,
      "extra": {
        "t": "beforeinput"
      }
    },
    {
      "_trace": true,
      "kind": "event",
      "url": "https://conxa.pipedrive.com/persons/list/user/everyone?quickFilter=none",
      "ts": 1779853393596,
      "extra": {
        "t": "input"
      }
    },
    {
      "_trace": true,
      "kind": "event",
      "url": "https://conxa.pipedrive.com/persons/list/user/everyone?quickFilter=none",
      "ts": 1779853393760,
      "extra": {
        "t": "beforeinput"
      }
    },
    {
      "_trace": true,
      "kind": "event",
      "url": "https://conxa.pipedrive.com/persons/list/user/everyone?quickFilter=none",
      "ts": 1779853393760,
      "extra": {
        "t": "input"
      }
    },
    {
      "_trace": true,
      "kind": "event",
      "url": "https://conxa.pipedrive.com/persons/list/user/everyone?quickFilter=none",
      "ts": 1779853394013,
      "extra": {
        "t": "beforeinput"
      }
    },
    {
      "_trace": true,
      "kind": "event",
      "url": "https://conxa.pipedrive.com/persons/list/user/everyone?quickFilter=none",
      "ts": 1779853394015,
      "extra": {
        "t": "input"
      }
    },
    {
      "_trace": true,
      "kind": "event",
      "url": "https://conxa.pipedrive.com/persons/list/user/everyone?quickFilter=none",
      "ts": 1779853394162,
      "extra": {
        "t": "beforeinput"
      }
    },
    {
      "_trace": true,
      "kind": "event",
      "url": "https://conxa.pipedrive.com/persons/list/user/everyone?quickFilter=none",
      "ts": 1779853394164,
      "extra": {
        "t": "input"
      }
    },
    {
      "_trace": true,
      "kind": "event",
      "url": "https://conxa.pipedrive.com/persons/list/user/everyone?quickFilter=none",
      "ts": 1779853394358,
      "extra": {
        "t": "beforeinput"
      }
    },
    {
      "_trace": true,
      "kind": "event",
      "url": "https://conxa.pipedrive.com/persons/list/user/everyone?quickFilter=none",
      "ts": 1779853394359,
      "extra": {
        "t": "input"
      }
    },
    {
      "_trace": true,
      "kind": "event",
      "url": "https://conxa.pipedrive.com/persons/list/user/everyone?quickFilter=none",
      "ts": 1779853395826,
      "extra": {
        "t": "focusout"
      }
    },
    {
      "_trace": true,
      "kind": "event",
      "url": "https://conxa.pipedrive.com/persons/list/user/everyone?quickFilter=none",
      "ts": 1779853395829,
      "extra": {
        "t": "focusin"
      }
    },
    {
      "_trace": true,
      "kind": "event",
      "url": "https://conxa.pipedrive.com/persons/list/user/everyone?quickFilter=none",
      "ts": 1779853396044,
      "extra": {
        "t": "click"
      }
    },
    {
      "_trace": true,
      "kind": "event",
      "url": "https://conxa.pipedrive.com/persons/list/user/everyone?quickFilter=none",
      "ts": 1779853396582,
      "extra": {
        "t": "beforeinput"
      }
    },
    {
      "_trace": true,
      "kind": "event",
      "url": "https://conxa.pipedrive.com/persons/list/user/everyone?quickFilter=none",
      "ts": 1779853396583,
      "extra": {
        "t": "input"
      }
    },
    {
      "_trace": true,
      "kind": "event",
      "url": "https://conxa.pipedrive.com/persons/list/user/everyone?quickFilter=none",
      "ts": 1779853396894,
      "extra": {
        "t": "beforeinput"
      }
    },
    {
      "_trace": true,
      "kind": "event",
      "url": "https://conxa.pipedrive.com/persons/list/user/everyone?quickFilter=none",
      "ts": 1779853396896,
      "extra": {
        "t": "input"
      }
    },
    {
      "_trace": true,
      "kind": "event",
      "url": "https://conxa.pipedrive.com/persons/list/user/everyone?quickFilter=none",
      "ts": 1779853397112,
      "extra": {
        "t": "beforeinput"
      }
    },
    {
      "_trace": true,
      "kind": "event",
      "url": "https://conxa.pipedrive.com/persons/list/user/everyone?quickFilter=none",
      "ts": 1779853397113,
      "extra": {
        "t": "input"
      }
    },
    {
      "_trace": true,
      "kind": "event",
      "url": "https://conxa.pipedrive.com/persons/list/user/everyone?quickFilter=none",
      "ts": 1779853397419,
      "extra": {
        "t": "beforeinput"
      }
    },
    {
      "_trace": true,
      "kind": "event",
      "url": "https://conxa.pipedrive.com/persons/list/user/everyone?quickFilter=none",
      "ts": 1779853397421,
      "extra": {
        "t": "input"
      }
    },
    {
      "_trace": true,
      "kind": "event",
      "url": "https://conxa.pipedrive.com/persons/list/user/everyone?quickFilter=none",
      "ts": 1779853397591,
      "extra": {
        "t": "beforeinput"
      }
    },
    {
      "_trace": true,
      "kind": "event",
      "url": "https://conxa.pipedrive.com/persons/list/user/everyone?quickFilter=none",
      "ts": 1779853397592,
      "extra": {
        "t": "input"
      }
    },
    {
      "_trace": true,
      "kind": "event",
      "url": "https://conxa.pipedrive.com/persons/list/user/everyone?quickFilter=none",
      "ts": 1779853397794,
      "extra": {
        "t": "beforeinput"
      }
    },
    {
      "_trace": true,
      "kind": "event",
      "url": "https://conxa.pipedrive.com/persons/list/user/everyone?quickFilter=none",
      "ts": 1779853397795,
      "extra": {
        "t": "input"
      }
    },
    {
      "_trace": true,
      "kind": "event",
      "url": "https://conxa.pipedrive.com/persons/list/user/everyone?quickFilter=none",
      "ts": 1779853401523,
      "extra": {
        "t": "focusout"
      }
    },
    {
      "_trace": true,
      "kind": "event",
      "url": "https://conxa.pipedrive.com/persons/list/user/everyone?quickFilter=none",
      "ts": 1779853401524,
      "extra": {
        "t": "focusin"
      }
    },
    {
      "_trace": true,
      "kind": "event",
      "url": "https://conxa.pipedrive.com/persons/list/user/everyone?quickFilter=none",
      "ts": 1779853401750,
      "extra": {
        "t": "click"
      }
    },
    {
      "_trace": true,
      "kind": "event",
      "url": "https://conxa.pipedrive.com/persons/list/user/everyone?quickFilter=none",
      "ts": 1779853402296,
      "extra": {
        "t": "beforeinput"
      }
    },
    {
      "_trace": true,
      "kind": "event",
      "url": "https://conxa.pipedrive.com/persons/list/user/everyone?quickFilter=none",
      "ts": 1779853402297,
      "extra": {
        "t": "input"
      }
    },
    {
      "_trace": true,
      "kind": "event",
      "url": "https://conxa.pipedrive.com/persons/list/user/everyone?quickFilter=none",
      "ts": 1779853402487,
      "extra": {
        "t": "beforeinput"
      }
    },
    {
      "_trace": true,
      "kind": "event",
      "url": "https://conxa.pipedrive.com/persons/list/user/everyone?quickFilter=none",
      "ts": 1779853402488,
      "extra": {
        "t": "input"
      }
    },
    {
      "_trace": true,
      "kind": "event",
      "url": "https://conxa.pipedrive.com/persons/list/user/everyone?quickFilter=none",
      "ts": 1779853402824,
      "extra": {
        "t": "beforeinput"
      }
    },
    {
      "_trace": true,
      "kind": "event",
      "url": "https://conxa.pipedrive.com/persons/list/user/everyone?quickFilter=none",
      "ts": 1779853402824,
      "extra": {
        "t": "input"
      }
    },
    {
      "_trace": true,
      "kind": "event",
      "url": "https://conxa.pipedrive.com/persons/list/user/everyone?quickFilter=none",
      "ts": 1779853403083,
      "extra": {
        "t": "beforeinput"
      }
    },
    {
      "_trace": true,
      "kind": "event",
      "url": "https://conxa.pipedrive.com/persons/list/user/everyone?quickFilter=none",
      "ts": 1779853403084,
      "extra": {
        "t": "input"
      }
    },
    {
      "_trace": true,
      "kind": "event",
      "url": "https://conxa.pipedrive.com/persons/list/user/everyone?quickFilter=none",
      "ts": 1779853403262,
      "extra": {
        "t": "beforeinput"
      }
    },
    {
      "_trace": true,
      "kind": "event",
      "url": "https://conxa.pipedrive.com/persons/list/user/everyone?quickFilter=none",
      "ts": 1779853403263,
      "extra": {
        "t": "input"
      }
    },
    {
      "_trace": true,
      "kind": "event",
      "url": "https://conxa.pipedrive.com/persons/list/user/everyone?quickFilter=none",
      "ts": 1779853403405,
      "extra": {
        "t": "beforeinput"
      }
    },
    {
      "_trace": true,
      "kind": "event",
      "url": "https://conxa.pipedrive.com/persons/list/user/everyone?quickFilter=none",
      "ts": 1779853403406,
      "extra": {
        "t": "input"
      }
    },
    {
      "_trace": true,
      "kind": "event",
      "url": "https://conxa.pipedrive.com/persons/list/user/everyone?quickFilter=none",
      "ts": 1779853403539,
      "extra": {
        "t": "beforeinput"
      }
    },
    {
      "_trace": true,
      "kind": "event",
      "url": "https://conxa.pipedrive.com/persons/list/user/everyone?quickFilter=none",
      "ts": 1779853403540,
      "extra": {
        "t": "input"
      }
    },
    {
      "_trace": true,
      "kind": "event",
      "url": "https://conxa.pipedrive.com/persons/list/user/everyone?quickFilter=none",
      "ts": 1779853403816,
      "extra": {
        "t": "beforeinput"
      }
    },
    {
      "_trace": true,
      "kind": "event",
      "url": "https://conxa.pipedrive.com/persons/list/user/everyone?quickFilter=none",
      "ts": 1779853403817,
      "extra": {
        "t": "input"
      }
    },
    {
      "_trace": true,
      "kind": "event",
      "url": "https://conxa.pipedrive.com/persons/list/user/everyone?quickFilter=none",
      "ts": 1779853403958,
      "extra": {
        "t": "beforeinput"
      }
    },
    {
      "_trace": true,
      "kind": "event",
      "url": "https://conxa.pipedrive.com/persons/list/user/everyone?quickFilter=none",
      "ts": 1779853403959,
      "extra": {
        "t": "input"
      }
    },
    {
      "_trace": true,
      "kind": "event",
      "url": "https://conxa.pipedrive.com/persons/list/user/everyone?quickFilter=none",
      "ts": 1779853405145,
      "extra": {
        "t": "focusout"
      }
    },
    {
      "_trace": true,
      "kind": "event",
      "url": "https://conxa.pipedrive.com/persons/list/user/everyone?quickFilter=none",
      "ts": 1779853405146,
      "extra": {
        "t": "focusin"
      }
    },
    {
      "_trace": true,
      "kind": "event",
      "url": "https://conxa.pipedrive.com/persons/list/user/everyone?quickFilter=none",
      "ts": 1779853405359,
      "extra": {
        "t": "click"
      }
    },
    {
      "_trace": true,
      "kind": "event",
      "url": "https://conxa.pipedrive.com/persons/list/user/everyone?quickFilter=none",
      "ts": 1779853406368,
      "extra": {
        "t": "beforeinput"
      }
    },
    {
      "_trace": true,
      "kind": "event",
      "url": "https://conxa.pipedrive.com/persons/list/user/everyone?quickFilter=none",
      "ts": 1779853406369,
      "extra": {
        "t": "input"
      }
    },
    {
      "_trace": true,
      "kind": "event",
      "url": "https://conxa.pipedrive.com/persons/list/user/everyone?quickFilter=none",
      "ts": 1779853406580,
      "extra": {
        "t": "beforeinput"
      }
    },
    {
      "_trace": true,
      "kind": "event",
      "url": "https://conxa.pipedrive.com/persons/list/user/everyone?quickFilter=none",
      "ts": 1779853406581,
      "extra": {
        "t": "input"
      }
    },
    {
      "_trace": true,
      "kind": "event",
      "url": "https://conxa.pipedrive.com/persons/list/user/everyone?quickFilter=none",
      "ts": 1779853406784,
      "extra": {
        "t": "beforeinput"
      }
    },
    {
      "_trace": true,
      "kind": "event",
      "url": "https://conxa.pipedrive.com/persons/list/user/everyone?quickFilter=none",
      "ts": 1779853406784,
      "extra": {
        "t": "input"
      }
    },
    {
      "_trace": true,
      "kind": "event",
      "url": "https://conxa.pipedrive.com/persons/list/user/everyone?quickFilter=none",
      "ts": 1779853406936,
      "extra": {
        "t": "beforeinput"
      }
    },
    {
      "_trace": true,
      "kind": "event",
      "url": "https://conxa.pipedrive.com/persons/list/user/everyone?quickFilter=none",
      "ts": 1779853406937,
      "extra": {
        "t": "input"
      }
    },
    {
      "_trace": true,
      "kind": "event",
      "url": "https://conxa.pipedrive.com/persons/list/user/everyone?quickFilter=none",
      "ts": 1779853407130,
      "extra": {
        "t": "beforeinput"
      }
    },
    {
      "_trace": true,
      "kind": "event",
      "url": "https://conxa.pipedrive.com/persons/list/user/everyone?quickFilter=none",
      "ts": 1779853407131,
      "extra": {
        "t": "input"
      }
    },
    {
      "_trace": true,
      "kind": "event",
      "url": "https://conxa.pipedrive.com/persons/list/user/everyone?quickFilter=none",
      "ts": 1779853407278,
      "extra": {
        "t": "beforeinput"
      }
    },
    {
      "_trace": true,
      "kind": "event",
      "url": "https://conxa.pipedrive.com/persons/list/user/everyone?quickFilter=none",
      "ts": 1779853407279,
      "extra": {
        "t": "input"
      }
    },
    {
      "_trace": true,
      "kind": "event",
      "url": "https://conxa.pipedrive.com/persons/list/user/everyone?quickFilter=none",
      "ts": 1779853407450,
      "extra": {
        "t": "beforeinput"
      }
    },
    {
      "_trace": true,
      "kind": "event",
      "url": "https://conxa.pipedrive.com/persons/list/user/everyone?quickFilter=none",
      "ts": 1779853407450,
      "extra": {
        "t": "input"
      }
    },
    {
      "_trace": true,
      "kind": "event",
      "url": "https://conxa.pipedrive.com/persons/list/user/everyone?quickFilter=none",
      "ts": 1779853407910,
      "extra": {
        "t": "beforeinput"
      }
    },
    {
      "_trace": true,
      "kind": "event",
      "url": "https://conxa.pipedrive.com/persons/list/user/everyone?quickFilter=none",
      "ts": 1779853407912,
      "extra": {
        "t": "input"
      }
    },
    {
      "_trace": true,
      "kind": "event",
      "url": "https://conxa.pipedrive.com/persons/list/user/everyone?quickFilter=none",
      "ts": 1779853408128,
      "extra": {
        "t": "beforeinput"
      }
    },
    {
      "_trace": true,
      "kind": "event",
      "url": "https://conxa.pipedrive.com/persons/list/user/everyone?quickFilter=none",
      "ts": 1779853408129,
      "extra": {
        "t": "input"
      }
    },
    {
      "_trace": true,
      "kind": "event",
      "url": "https://conxa.pipedrive.com/persons/list/user/everyone?quickFilter=none",
      "ts": 1779853408319,
      "extra": {
        "t": "beforeinput"
      }
    },
    {
      "_trace": true,
      "kind": "event",
      "url": "https://conxa.pipedrive.com/persons/list/user/everyone?quickFilter=none",
      "ts": 1779853408320,
      "extra": {
        "t": "input"
      }
    },
    {
      "_trace": true,
      "kind": "event",
      "url": "https://conxa.pipedrive.com/persons/list/user/everyone?quickFilter=none",
      "ts": 1779853408850,
      "extra": {
        "t": "beforeinput"
      }
    },
    {
      "_trace": true,
      "kind": "event",
      "url": "https://conxa.pipedrive.com/persons/list/user/everyone?quickFilter=none",
      "ts": 1779853408851,
      "extra": {
        "t": "input"
      }
    },
    {
      "_trace": true,
      "kind": "event",
      "url": "https://conxa.pipedrive.com/persons/list/user/everyone?quickFilter=none",
      "ts": 1779853409010,
      "extra": {
        "t": "beforeinput"
      }
    },
    {
      "_trace": true,
      "kind": "event",
      "url": "https://conxa.pipedrive.com/persons/list/user/everyone?quickFilter=none",
      "ts": 1779853409011,
      "extra": {
        "t": "input"
      }
    },
    {
      "_trace": true,
      "kind": "event",
      "url": "https://conxa.pipedrive.com/persons/list/user/everyone?quickFilter=none",
      "ts": 1779853409186,
      "extra": {
        "t": "beforeinput"
      }
    },
    {
      "_trace": true,
      "kind": "event",
      "url": "https://conxa.pipedrive.com/persons/list/user/everyone?quickFilter=none",
      "ts": 1779853409186,
      "extra": {
        "t": "input"
      }
    },
    {
      "_trace": true,
      "kind": "event",
      "url": "https://conxa.pipedrive.com/persons/list/user/everyone?quickFilter=none",
      "ts": 1779853409738,
      "extra": {
        "t": "beforeinput"
      }
    },
    {
      "_trace": true,
      "kind": "event",
      "url": "https://conxa.pipedrive.com/persons/list/user/everyone?quickFilter=none",
      "ts": 1779853409739,
      "extra": {
        "t": "input"
      }
    },
    {
      "_trace": true,
      "kind": "event",
      "url": "https://conxa.pipedrive.com/persons/list/user/everyone?quickFilter=none",
      "ts": 1779853410414,
      "extra": {
        "t": "beforeinput"
      }
    },
    {
      "_trace": true,
      "kind": "event",
      "url": "https://conxa.pipedrive.com/persons/list/user/everyone?quickFilter=none",
      "ts": 1779853410414,
      "extra": {
        "t": "input"
      }
    },
    {
      "_trace": true,
      "kind": "event",
      "url": "https://conxa.pipedrive.com/persons/list/user/everyone?quickFilter=none",
      "ts": 1779853410615,
      "extra": {
        "t": "beforeinput"
      }
    },
    {
      "_trace": true,
      "kind": "event",
      "url": "https://conxa.pipedrive.com/persons/list/user/everyone?quickFilter=none",
      "ts": 1779853410616,
      "extra": {
        "t": "input"
      }
    },
    {
      "_trace": true,
      "kind": "event",
      "url": "https://conxa.pipedrive.com/persons/list/user/everyone?quickFilter=none",
      "ts": 1779853410886,
      "extra": {
        "t": "beforeinput"
      }
    },
    {
      "_trace": true,
      "kind": "event",
      "url": "https://conxa.pipedrive.com/persons/list/user/everyone?quickFilter=none",
      "ts": 1779853410887,
      "extra": {
        "t": "input"
      }
    },
    {
      "_trace": true,
      "kind": "event",
      "url": "https://conxa.pipedrive.com/persons/list/user/everyone?quickFilter=none",
      "ts": 1779853411048,
      "extra": {
        "t": "beforeinput"
      }
    },
    {
      "_trace": true,
      "kind": "event",
      "url": "https://conxa.pipedrive.com/persons/list/user/everyone?quickFilter=none",
      "ts": 1779853411049,
      "extra": {
        "t": "input"
      }
    },
    {
      "_trace": true,
      "kind": "event",
      "url": "https://conxa.pipedrive.com/persons/list/user/everyone?quickFilter=none",
      "ts": 1779853411172,
      "extra": {
        "t": "beforeinput"
      }
    },
    {
      "_trace": true,
      "kind": "event",
      "url": "https://conxa.pipedrive.com/persons/list/user/everyone?quickFilter=none",
      "ts": 1779853411172,
      "extra": {
        "t": "input"
      }
    },
    {
      "_trace": true,
      "kind": "event",
      "url": "https://conxa.pipedrive.com/persons/list/user/everyone?quickFilter=none",
      "ts": 1779853411496,
      "extra": {
        "t": "beforeinput"
      }
    },
    {
      "_trace": true,
      "kind": "event",
      "url": "https://conxa.pipedrive.com/persons/list/user/everyone?quickFilter=none",
      "ts": 1779853411498,
      "extra": {
        "t": "input"
      }
    },
    {
      "_trace": true,
      "kind": "event",
      "url": "https://conxa.pipedrive.com/persons/list/user/everyone?quickFilter=none",
      "ts": 1779853412039,
      "extra": {
        "t": "beforeinput"
      }
    },
    {
      "_trace": true,
      "kind": "event",
      "url": "https://conxa.pipedrive.com/persons/list/user/everyone?quickFilter=none",
      "ts": 1779853412041,
      "extra": {
        "t": "input"
      }
    },
    {
      "_trace": true,
      "kind": "event",
      "url": "https://conxa.pipedrive.com/persons/list/user/everyone?quickFilter=none",
      "ts": 1779853412268,
      "extra": {
        "t": "beforeinput"
      }
    },
    {
      "_trace": true,
      "kind": "event",
      "url": "https://conxa.pipedrive.com/persons/list/user/everyone?quickFilter=none",
      "ts": 1779853412269,
      "extra": {
        "t": "input"
      }
    },
    {
      "_trace": true,
      "kind": "event",
      "url": "https://conxa.pipedrive.com/persons/list/user/everyone?quickFilter=none",
      "ts": 1779853412389,
      "extra": {
        "t": "beforeinput"
      }
    },
    {
      "_trace": true,
      "kind": "event",
      "url": "https://conxa.pipedrive.com/persons/list/user/everyone?quickFilter=none",
      "ts": 1779853412391,
      "extra": {
        "t": "input"
      }
    },
    {
      "_trace": true,
      "kind": "event",
      "url": "https://conxa.pipedrive.com/persons/list/user/everyone?quickFilter=none",
      "ts": 1779853412544,
      "extra": {
        "t": "beforeinput"
      }
    },
    {
      "_trace": true,
      "kind": "event",
      "url": "https://conxa.pipedrive.com/persons/list/user/everyone?quickFilter=none",
      "ts": 1779853412545,
      "extra": {
        "t": "input"
      }
    },
    {
      "_trace": true,
      "kind": "event",
      "url": "https://conxa.pipedrive.com/persons/list/user/everyone?quickFilter=none",
      "ts": 1779853412740,
      "extra": {
        "t": "beforeinput"
      }
    },
    {
      "_trace": true,
      "kind": "event",
      "url": "https://conxa.pipedrive.com/persons/list/user/everyone?quickFilter=none",
      "ts": 1779853412741,
      "extra": {
        "t": "input"
      }
    },
    {
      "_trace": true,
      "kind": "event",
      "url": "https://conxa.pipedrive.com/persons/list/user/everyone?quickFilter=none",
      "ts": 1779853413151,
      "extra": {
        "t": "beforeinput"
      }
    },
    {
      "_trace": true,
      "kind": "event",
      "url": "https://conxa.pipedrive.com/persons/list/user/everyone?quickFilter=none",
      "ts": 1779853413152,
      "extra": {
        "t": "input"
      }
    },
    {
      "_trace": true,
      "kind": "event",
      "url": "https://conxa.pipedrive.com/persons/list/user/everyone?quickFilter=none",
      "ts": 1779853413374,
      "extra": {
        "t": "beforeinput"
      }
    },
    {
      "_trace": true,
      "kind": "event",
      "url": "https://conxa.pipedrive.com/persons/list/user/everyone?quickFilter=none",
      "ts": 1779853413375,
      "extra": {
        "t": "input"
      }
    },
    {
      "_trace": true,
      "kind": "event",
      "url": "https://conxa.pipedrive.com/persons/list/user/everyone?quickFilter=none",
      "ts": 1779853413569,
      "extra": {
        "t": "beforeinput"
      }
    },
    {
      "_trace": true,
      "kind": "event",
      "url": "https://conxa.pipedrive.com/persons/list/user/everyone?quickFilter=none",
      "ts": 1779853413570,
      "extra": {
        "t": "input"
      }
    },
    {
      "_trace": true,
      "kind": "event",
      "url": "https://conxa.pipedrive.com/persons/list/user/everyone?quickFilter=none",
      "ts": 1779853413729,
      "extra": {
        "t": "beforeinput"
      }
    },
    {
      "_trace": true,
      "kind": "event",
      "url": "https://conxa.pipedrive.com/persons/list/user/everyone?quickFilter=none",
      "ts": 1779853413731,
      "extra": {
        "t": "input"
      }
    },
    {
      "_trace": true,
      "kind": "event",
      "url": "https://conxa.pipedrive.com/persons/list/user/everyone?quickFilter=none",
      "ts": 1779853415125,
      "extra": {
        "t": "focusout"
      }
    },
    {
      "_trace": true,
      "kind": "event",
      "url": "https://conxa.pipedrive.com/persons/list/user/everyone?quickFilter=none",
      "ts": 1779853415126,
      "extra": {
        "t": "focusin"
      }
    },
    {
      "_trace": true,
      "kind": "event",
      "url": "https://conxa.pipedrive.com/persons/list/user/everyone?quickFilter=none",
      "ts": 1779853415353,
      "extra": {
        "t": "click"
      }
    },
    {
      "_trace": true,
      "kind": "event",
      "url": "https://conxa.pipedrive.com/persons/list/user/everyone?quickFilter=none",
      "ts": 1779853415394,
      "extra": {
        "t": "focusout"
      }
    },
    {
      "_trace": true,
      "kind": "event",
      "url": "https://conxa.pipedrive.com/persons/list/user/everyone?quickFilter=none",
      "ts": 1779853415394,
      "extra": {
        "t": "focusin"
      }
    },
    {
      "_trace": true,
      "kind": "event",
      "url": "https://conxa.pipedrive.com/persons/list/user/everyone?quickFilter=none",
      "ts": 1779853416270,
      "extra": {
        "t": "focusout"
      }
    },
    {
      "_trace": true,
      "kind": "event",
      "url": "https://conxa.pipedrive.com/persons/list/user/everyone?quickFilter=none",
      "ts": 1779853416496,
      "extra": {
        "t": "click"
      }
    },
    {
      "_trace": true,
      "kind": "event",
      "url": "https://conxa.pipedrive.com/persons/list/user/everyone?quickFilter=none",
      "ts": 1779853420027,
      "extra": {
        "t": "click"
      }
    },
    {
      "_trace": true,
      "kind": "event",
      "url": "https://conxa.pipedrive.com/persons/list/user/everyone?quickFilter=none",
      "ts": 1779853420976,
      "extra": {
        "t": "focusin"
      }
    },
    {
      "_trace": true,
      "kind": "event",
      "url": "https://conxa.pipedrive.com/persons/list/user/everyone?quickFilter=none",
      "ts": 1779853421198,
      "extra": {
        "t": "click"
      }
    },
    {
      "_trace": true,
      "kind": "event",
      "url": "https://conxa.pipedrive.com/persons/list/user/everyone?quickFilter=none",
      "ts": 1779853421990,
      "extra": {
        "t": "focusout"
      }
    },
    {
      "_trace": true,
      "kind": "event",
      "url": "https://conxa.pipedrive.com/persons/list/user/everyone?quickFilter=none",
      "ts": 1779853421991,
      "extra": {
        "t": "focusin"
      }
    },
    {
      "_trace": true,
      "kind": "event",
      "url": "https://conxa.pipedrive.com/persons/list/user/everyone?quickFilter=none",
      "ts": 1779853422228,
      "extra": {
        "t": "click"
      }
    },
    {
      "_trace": true,
      "kind": "event",
      "url": "https://conxa.pipedrive.com/persons/list/user/everyone?quickFilter=none",
      "ts": 1779853422262,
      "extra": {
        "t": "focusout"
      }
    },
    {
      "_trace": true,
      "kind": "event",
      "url": "https://conxa.pipedrive.com/persons/list/user/everyone?quickFilter=none",
      "ts": 1779853423382,
      "extra": {
        "t": "focusin"
      }
    },
    {
      "_trace": true,
      "kind": "event",
      "url": "https://conxa.pipedrive.com/persons/list/user/everyone?quickFilter=none",
      "ts": 1779853423612,
      "extra": {
        "t": "click"
      }
    },
    {
      "_trace": true,
      "kind": "event",
      "url": "https://conxa.pipedrive.com/persons/list/user/everyone?quickFilter=none",
      "ts": 1779853424254,
      "extra": {
        "t": "focusout"
      }
    }
  ],
  "frame_tree": [],
  "frame_snapshots": [
    {
      "ts": 1779853350331,
      "frames": [
        {
          "url": "https://conxa.pipedrive.com/setup-guide",
          "parent_url": null
        },
        {
          "url": "about:blank",
          "parent_url": "https://conxa.pipedrive.com/setup-guide"
        },
        {
          "url": "about:blank",
          "parent_url": "https://conxa.pipedrive.com/setup-guide"
        }
      ]
    },
    {
      "ts": 1779853351548,
      "frames": [
        {
          "url": "https://conxa.pipedrive.com/setup-guide",
          "parent_url": null
        },
        {
          "url": "about:blank",
          "parent_url": "https://conxa.pipedrive.com/setup-guide"
        },
        {
          "url": "about:blank",
          "parent_url": "https://conxa.pipedrive.com/setup-guide"
        }
      ]
    },
    {
      "ts": 1779853352739,
      "frames": [
        {
          "url": "https://conxa.pipedrive.com/setup-guide",
          "parent_url": null
        },
        {
          "url": "about:blank",
          "parent_url": "https://conxa.pipedrive.com/setup-guide"
        },
        {
          "url": "about:blank",
          "parent_url": "https://conxa.pipedrive.com/setup-guide"
        }
      ]
    },
    {
      "ts": 1779853353884,
      "frames": [
        {
          "url": "https://conxa.pipedrive.com/setup-guide",
          "parent_url": null
        },
        {
          "url": "about:blank",
          "parent_url": "https://conxa.pipedrive.com/setup-guide"
        },
        {
          "url": "about:blank",
          "parent_url": "https://conxa.pipedrive.com/setup-guide"
        }
      ]
    },
    {
      "ts": 1779853354997,
      "frames": [
        {
          "url": "https://conxa.pipedrive.com/setup-guide",
          "parent_url": null
        },
        {
          "url": "about:blank",
          "parent_url": "https://conxa.pipedrive.com/setup-guide"
        },
        {
          "url": "about:blank",
          "parent_url": "https://conxa.pipedrive.com/setup-guide"
        }
      ]
    },
    {
      "ts": 1779853356149,
      "frames": [
        {
          "url": "https://conxa.pipedrive.com/setup-guide",
          "parent_url": null
        },
        {
          "url": "about:blank",
          "parent_url": "https://conxa.pipedrive.com/setup-guide"
        },
        {
          "url": "about:blank",
          "parent_url": "https://conxa.pipedrive.com/setup-guide"
        }
      ]
    },
    {
      "ts": 1779853357281,
      "frames": [
        {
          "url": "https://conxa.pipedrive.com/setup-guide",
          "parent_url": null
        },
        {
          "url": "about:blank",
          "parent_url": "https://conxa.pipedrive.com/setup-guide"
        },
        {
          "url": "about:blank",
          "parent_url": "https://conxa.pipedrive.com/setup-guide"
        }
      ]
    },
    {
      "ts": 1779853358436,
      "frames": [
        {
          "url": "https://conxa.pipedrive.com/setup-guide",
          "parent_url": null
        },
        {
          "url": "about:blank",
          "parent_url": "https://conxa.pipedrive.com/setup-guide"
        },
        {
          "url": "about:blank",
          "parent_url": "https://conxa.pipedrive.com/setup-guide"
        }
      ]
    },
    {
      "ts": 1779853359560,
      "frames": [
        {
          "url": "https://conxa.pipedrive.com/setup-guide",
          "parent_url": null
        },
        {
          "url": "about:blank",
          "parent_url": "https://conxa.pipedrive.com/setup-guide"
        },
        {
          "url": "about:blank",
          "parent_url": "https://conxa.pipedrive.com/setup-guide"
        }
      ]
    },
    {
      "ts": 1779853360708,
      "frames": [
        {
          "url": "https://conxa.pipedrive.com/setup-guide",
          "parent_url": null
        },
        {
          "url": "about:blank",
          "parent_url": "https://conxa.pipedrive.com/setup-guide"
        },
        {
          "url": "about:blank",
          "parent_url": "https://conxa.pipedrive.com/setup-guide"
        }
      ]
    },
    {
      "ts": 1779853361895,
      "frames": [
        {
          "url": "https://conxa.pipedrive.com/setup-guide",
          "parent_url": null
        },
        {
          "url": "about:blank",
          "parent_url": "https://conxa.pipedrive.com/setup-guide"
        },
        {
          "url": "about:blank",
          "parent_url": "https://conxa.pipedrive.com/setup-guide"
        }
      ]
    },
    {
      "ts": 1779853363034,
      "frames": [
        {
          "url": "https://conxa.pipedrive.com/setup-guide",
          "parent_url": null
        },
        {
          "url": "about:blank",
          "parent_url": "https://conxa.pipedrive.com/setup-guide"
        },
        {
          "url": "about:blank",
          "parent_url": "https://conxa.pipedrive.com/setup-guide"
        }
      ]
    },
    {
      "ts": 1779853364180,
      "frames": [
        {
          "url": "https://conxa.pipedrive.com/setup-guide",
          "parent_url": null
        },
        {
          "url": "about:blank",
          "parent_url": "https://conxa.pipedrive.com/setup-guide"
        },
        {
          "url": "about:blank",
          "parent_url": "https://conxa.pipedrive.com/setup-guide"
        }
      ]
    },
    {
      "ts": 1779853365313,
      "frames": [
        {
          "url": "https://conxa.pipedrive.com/setup-guide",
          "parent_url": null
        },
        {
          "url": "about:blank",
          "parent_url": "https://conxa.pipedrive.com/setup-guide"
        },
        {
          "url": "about:blank",
          "parent_url": "https://conxa.pipedrive.com/setup-guide"
        }
      ]
    },
    {
      "ts": 1779853366526,
      "frames": [
        {
          "url": "https://conxa.pipedrive.com/setup-guide",
          "parent_url": null
        },
        {
          "url": "about:blank",
          "parent_url": "https://conxa.pipedrive.com/setup-guide"
        },
        {
          "url": "about:blank",
          "parent_url": "https://conxa.pipedrive.com/setup-guide"
        }
      ]
    },
    {
      "ts": 1779853367663,
      "frames": [
        {
          "url": "https://conxa.pipedrive.com/setup-guide",
          "parent_url": null
        },
        {
          "url": "about:blank",
          "parent_url": "https://conxa.pipedrive.com/setup-guide"
        },
        {
          "url": "about:blank",
          "parent_url": "https://conxa.pipedrive.com/setup-guide"
        }
      ]
    },
    {
      "ts": 1779853368794,
      "frames": [
        {
          "url": "https://conxa.pipedrive.com/setup-guide",
          "parent_url": null
        },
        {
          "url": "about:blank",
          "parent_url": "https://conxa.pipedrive.com/setup-guide"
        },
        {
          "url": "about:blank",
          "parent_url": "https://conxa.pipedrive.com/setup-guide"
        }
      ]
    },
    {
      "ts": 1779853369967,
      "frames": [
        {
          "url": "https://conxa.pipedrive.com/setup-guide",
          "parent_url": null
        },
        {
          "url": "about:blank",
          "parent_url": "https://conxa.pipedrive.com/setup-guide"
        },
        {
          "url": "about:blank",
          "parent_url": "https://conxa.pipedrive.com/setup-guide"
        }
      ]
    },
    {
      "ts": 1779853371103,
      "frames": [
        {
          "url": "https://conxa.pipedrive.com/setup-guide",
          "parent_url": null
        },
        {
          "url": "about:blank",
          "parent_url": "https://conxa.pipedrive.com/setup-guide"
        },
        {
          "url": "about:blank",
          "parent_url": "https://conxa.pipedrive.com/setup-guide"
        }
      ]
    },
    {
      "ts": 1779853372219,
      "frames": [
        {
          "url": "https://conxa.pipedrive.com/setup-guide",
          "parent_url": null
        },
        {
          "url": "about:blank",
          "parent_url": "https://conxa.pipedrive.com/setup-guide"
        },
        {
          "url": "about:blank",
          "parent_url": "https://conxa.pipedrive.com/setup-guide"
        }
      ]
    },
    {
      "ts": 1779853373331,
      "frames": [
        {
          "url": "https://conxa.pipedrive.com/setup-guide",
          "parent_url": null
        },
        {
          "url": "about:blank",
          "parent_url": "https://conxa.pipedrive.com/setup-guide"
        },
        {
          "url": "about:blank",
          "parent_url": "https://conxa.pipedrive.com/setup-guide"
        }
      ]
    },
    {
      "ts": 1779853374483,
      "frames": [
        {
          "url": "https://conxa.pipedrive.com/setup-guide",
          "parent_url": null
        },
        {
          "url": "about:blank",
          "parent_url": "https://conxa.pipedrive.com/setup-guide"
        },
        {
          "url": "about:blank",
          "parent_url": "https://conxa.pipedrive.com/setup-guide"
        }
      ]
    },
    {
      "ts": 1779853375630,
      "frames": [
        {
          "url": "https://conxa.pipedrive.com/setup-guide",
          "parent_url": null
        },
        {
          "url": "about:blank",
          "parent_url": "https://conxa.pipedrive.com/setup-guide"
        },
        {
          "url": "about:blank",
          "parent_url": "https://conxa.pipedrive.com/setup-guide"
        }
      ]
    },
    {
      "ts": 1779853376763,
      "frames": [
        {
          "url": "https://conxa.pipedrive.com/setup-guide",
          "parent_url": null
        },
        {
          "url": "about:blank",
          "parent_url": "https://conxa.pipedrive.com/setup-guide"
        },
        {
          "url": "about:blank",
          "parent_url": "https://conxa.pipedrive.com/setup-guide"
        }
      ]
    },
    {
      "ts": 1779853377928,
      "frames": [
        {
          "url": "https://conxa.pipedrive.com/setup-guide",
          "parent_url": null
        },
        {
          "url": "about:blank",
          "parent_url": "https://conxa.pipedrive.com/setup-guide"
        },
        {
          "url": "about:blank",
          "parent_url": "https://conxa.pipedrive.com/setup-guide"
        }
      ]
    },
    {
      "ts": 1779853379058,
      "frames": [
        {
          "url": "https://conxa.pipedrive.com/setup-guide",
          "parent_url": null
        },
        {
          "url": "about:blank",
          "parent_url": "https://conxa.pipedrive.com/setup-guide"
        },
        {
          "url": "about:blank",
          "parent_url": "https://conxa.pipedrive.com/setup-guide"
        }
      ]
    },
    {
      "ts": 1779853380232,
      "frames": [
        {
          "url": "https://conxa.pipedrive.com/setup-guide",
          "parent_url": null
        },
        {
          "url": "about:blank",
          "parent_url": "https://conxa.pipedrive.com/setup-guide"
        },
        {
          "url": "about:blank",
          "parent_url": "https://conxa.pipedrive.com/setup-guide"
        }
      ]
    },
    {
      "ts": 1779853381368,
      "frames": [
        {
          "url": "https://conxa.pipedrive.com/setup-guide",
          "parent_url": null
        },
        {
          "url": "about:blank",
          "parent_url": "https://conxa.pipedrive.com/setup-guide"
        },
        {
          "url": "about:blank",
          "parent_url": "https://conxa.pipedrive.com/setup-guide"
        }
      ]
    },
    {
      "ts": 1779853382483,
      "frames": [
        {
          "url": "https://conxa.pipedrive.com/setup-guide",
          "parent_url": null
        },
        {
          "url": "about:blank",
          "parent_url": "https://conxa.pipedrive.com/setup-guide"
        },
        {
          "url": "about:blank",
          "parent_url": "https://conxa.pipedrive.com/setup-guide"
        }
      ]
    },
    {
      "ts": 1779853383625,
      "frames": [
        {
          "url": "https://conxa.pipedrive.com/setup-guide",
          "parent_url": null
        },
        {
          "url": "about:blank",
          "parent_url": "https://conxa.pipedrive.com/setup-guide"
        },
        {
          "url": "about:blank",
          "parent_url": "https://conxa.pipedrive.com/setup-guide"
        }
      ]
    },
    {
      "ts": 1779853384778,
      "frames": [
        {
          "url": "https://conxa.pipedrive.com/setup-guide",
          "parent_url": null
        },
        {
          "url": "about:blank",
          "parent_url": "https://conxa.pipedrive.com/setup-guide"
        },
        {
          "url": "about:blank",
          "parent_url": "https://conxa.pipedrive.com/setup-guide"
        }
      ]
    },
    {
      "ts": 1779853385935,
      "frames": [
        {
          "url": "https://conxa.pipedrive.com/setup-guide",
          "parent_url": null
        },
        {
          "url": "about:blank",
          "parent_url": "https://conxa.pipedrive.com/setup-guide"
        },
        {
          "url": "about:blank",
          "parent_url": "https://conxa.pipedrive.com/setup-guide"
        }
      ]
    },
    {
      "ts": 1779853387078,
      "frames": [
        {
          "url": "https://conxa.pipedrive.com/setup-guide",
          "parent_url": null
        },
        {
          "url": "about:blank",
          "parent_url": "https://conxa.pipedrive.com/setup-guide"
        },
        {
          "url": "about:blank",
          "parent_url": "https://conxa.pipedrive.com/setup-guide"
        }
      ]
    },
    {
      "ts": 1779853388189,
      "frames": [
        {
          "url": "https://conxa.pipedrive.com/setup-guide",
          "parent_url": null
        },
        {
          "url": "about:blank",
          "parent_url": "https://conxa.pipedrive.com/setup-guide"
        },
        {
          "url": "about:blank",
          "parent_url": "https://conxa.pipedrive.com/setup-guide"
        }
      ]
    },
    {
      "ts": 1779853390905,
      "frames": [
        {
          "url": "https://conxa.pipedrive.com/persons/list/user/everyone?quickFilter=none",
          "parent_url": null
        },
        {
          "url": "about:blank",
          "parent_url": "https://conxa.pipedrive.com/persons/list/user/everyone?quickFilter=none"
        },
        {
          "url": "about:blank",
          "parent_url": "https://conxa.pipedrive.com/persons/list/user/everyone?quickFilter=none"
        }
      ]
    },
    {
      "ts": 1779853392780,
      "frames": [
        {
          "url": "https://conxa.pipedrive.com/persons/list/user/everyone?quickFilter=none",
          "parent_url": null
        },
        {
          "url": "about:blank",
          "parent_url": "https://conxa.pipedrive.com/persons/list/user/everyone?quickFilter=none"
        },
        {
          "url": "about:blank",
          "parent_url": "https://conxa.pipedrive.com/persons/list/user/everyone?quickFilter=none"
        }
      ]
    },
    {
      "ts": 1779853393891,
      "frames": [
        {
          "url": "https://conxa.pipedrive.com/persons/list/user/everyone?quickFilter=none",
          "parent_url": null
        },
        {
          "url": "about:blank",
          "parent_url": "https://conxa.pipedrive.com/persons/list/user/everyone?quickFilter=none"
        },
        {
          "url": "about:blank",
          "parent_url": "https://conxa.pipedrive.com/persons/list/user/everyone?quickFilter=none"
        }
      ]
    },
    {
      "ts": 1779853395540,
      "frames": [
        {
          "url": "https://conxa.pipedrive.com/persons/list/user/everyone?quickFilter=none",
          "parent_url": null
        },
        {
          "url": "about:blank",
          "parent_url": "https://conxa.pipedrive.com/persons/list/user/everyone?quickFilter=none"
        },
        {
          "url": "about:blank",
          "parent_url": "https://conxa.pipedrive.com/persons/list/user/everyone?quickFilter=none"
        }
      ]
    },
    {
      "ts": 1779853396841,
      "frames": [
        {
          "url": "https://conxa.pipedrive.com/persons/list/user/everyone?quickFilter=none",
          "parent_url": null
        },
        {
          "url": "about:blank",
          "parent_url": "https://conxa.pipedrive.com/persons/list/user/everyone?quickFilter=none"
        },
        {
          "url": "about:blank",
          "parent_url": "https://conxa.pipedrive.com/persons/list/user/everyone?quickFilter=none"
        }
      ]
    },
    {
      "ts": 1779853397980,
      "frames": [
        {
          "url": "https://conxa.pipedrive.com/persons/list/user/everyone?quickFilter=none",
          "parent_url": null
        },
        {
          "url": "about:blank",
          "parent_url": "https://conxa.pipedrive.com/persons/list/user/everyone?quickFilter=none"
        },
        {
          "url": "about:blank",
          "parent_url": "https://conxa.pipedrive.com/persons/list/user/everyone?quickFilter=none"
        }
      ]
    },
    {
      "ts": 1779853399685,
      "frames": [
        {
          "url": "https://conxa.pipedrive.com/persons/list/user/everyone?quickFilter=none",
          "parent_url": null
        },
        {
          "url": "about:blank",
          "parent_url": "https://conxa.pipedrive.com/persons/list/user/everyone?quickFilter=none"
        },
        {
          "url": "about:blank",
          "parent_url": "https://conxa.pipedrive.com/persons/list/user/everyone?quickFilter=none"
        }
      ]
    },
    {
      "ts": 1779853400800,
      "frames": [
        {
          "url": "https://conxa.pipedrive.com/persons/list/user/everyone?quickFilter=none",
          "parent_url": null
        },
        {
          "url": "about:blank",
          "parent_url": "https://conxa.pipedrive.com/persons/list/user/everyone?quickFilter=none"
        },
        {
          "url": "about:blank",
          "parent_url": "https://conxa.pipedrive.com/persons/list/user/everyone?quickFilter=none"
        }
      ]
    },
    {
      "ts": 1779853403284,
      "frames": [
        {
          "url": "https://conxa.pipedrive.com/persons/list/user/everyone?quickFilter=none",
          "parent_url": null
        },
        {
          "url": "about:blank",
          "parent_url": "https://conxa.pipedrive.com/persons/list/user/everyone?quickFilter=none"
        },
        {
          "url": "about:blank",
          "parent_url": "https://conxa.pipedrive.com/persons/list/user/everyone?quickFilter=none"
        }
      ]
    },
    {
      "ts": 1779853404488,
      "frames": [
        {
          "url": "https://conxa.pipedrive.com/persons/list/user/everyone?quickFilter=none",
          "parent_url": null
        },
        {
          "url": "about:blank",
          "parent_url": "https://conxa.pipedrive.com/persons/list/user/everyone?quickFilter=none"
        },
        {
          "url": "about:blank",
          "parent_url": "https://conxa.pipedrive.com/persons/list/user/everyone?quickFilter=none"
        }
      ]
    },
    {
      "ts": 1779853406254,
      "frames": [
        {
          "url": "https://conxa.pipedrive.com/persons/list/user/everyone?quickFilter=none",
          "parent_url": null
        },
        {
          "url": "about:blank",
          "parent_url": "https://conxa.pipedrive.com/persons/list/user/everyone?quickFilter=none"
        },
        {
          "url": "about:blank",
          "parent_url": "https://conxa.pipedrive.com/persons/list/user/everyone?quickFilter=none"
        }
      ]
    },
    {
      "ts": 1779853407393,
      "frames": [
        {
          "url": "https://conxa.pipedrive.com/persons/list/user/everyone?quickFilter=none",
          "parent_url": null
        },
        {
          "url": "about:blank",
          "parent_url": "https://conxa.pipedrive.com/persons/list/user/everyone?quickFilter=none"
        },
        {
          "url": "about:blank",
          "parent_url": "https://conxa.pipedrive.com/persons/list/user/everyone?quickFilter=none"
        }
      ]
    },
    {
      "ts": 1779853408992,
      "frames": [
        {
          "url": "https://conxa.pipedrive.com/persons/list/user/everyone?quickFilter=none",
          "parent_url": null
        },
        {
          "url": "about:blank",
          "parent_url": "https://conxa.pipedrive.com/persons/list/user/everyone?quickFilter=none"
        },
        {
          "url": "about:blank",
          "parent_url": "https://conxa.pipedrive.com/persons/list/user/everyone?quickFilter=none"
        }
      ]
    },
    {
      "ts": 1779853411610,
      "frames": [
        {
          "url": "https://conxa.pipedrive.com/persons/list/user/everyone?quickFilter=none",
          "parent_url": null
        },
        {
          "url": "about:blank",
          "parent_url": "https://conxa.pipedrive.com/persons/list/user/everyone?quickFilter=none"
        },
        {
          "url": "about:blank",
          "parent_url": "https://conxa.pipedrive.com/persons/list/user/everyone?quickFilter=none"
        }
      ]
    },
    {
      "ts": 1779853413278,
      "frames": [
        {
          "url": "https://conxa.pipedrive.com/persons/list/user/everyone?quickFilter=none",
          "parent_url": null
        },
        {
          "url": "about:blank",
          "parent_url": "https://conxa.pipedrive.com/persons/list/user/everyone?quickFilter=none"
        },
        {
          "url": "about:blank",
          "parent_url": "https://conxa.pipedrive.com/persons/list/user/everyone?quickFilter=none"
        }
      ]
    },
    {
      "ts": 1779853414935,
      "frames": [
        {
          "url": "https://conxa.pipedrive.com/persons/list/user/everyone?quickFilter=none",
          "parent_url": null
        },
        {
          "url": "about:blank",
          "parent_url": "https://conxa.pipedrive.com/persons/list/user/everyone?quickFilter=none"
        },
        {
          "url": "about:blank",
          "parent_url": "https://conxa.pipedrive.com/persons/list/user/everyone?quickFilter=none"
        }
      ]
    },
    {
      "ts": 1779853416279,
      "frames": [
        {
          "url": "https://conxa.pipedrive.com/persons/list/user/everyone?quickFilter=none",
          "parent_url": null
        },
        {
          "url": "about:blank",
          "parent_url": "https://conxa.pipedrive.com/persons/list/user/everyone?quickFilter=none"
        },
        {
          "url": "about:blank",
          "parent_url": "https://conxa.pipedrive.com/persons/list/user/everyone?quickFilter=none"
        }
      ]
    },
    {
      "ts": 1779853417407,
      "frames": [
        {
          "url": "https://conxa.pipedrive.com/persons/list/user/everyone?quickFilter=none",
          "parent_url": null
        },
        {
          "url": "about:blank",
          "parent_url": "https://conxa.pipedrive.com/persons/list/user/everyone?quickFilter=none"
        },
        {
          "url": "about:blank",
          "parent_url": "https://conxa.pipedrive.com/persons/list/user/everyone?quickFilter=none"
        }
      ]
    },
    {
      "ts": 1779853419151,
      "frames": [
        {
          "url": "https://conxa.pipedrive.com/persons/list/user/everyone?quickFilter=none",
          "parent_url": null
        },
        {
          "url": "about:blank",
          "parent_url": "https://conxa.pipedrive.com/persons/list/user/everyone?quickFilter=none"
        },
        {
          "url": "about:blank",
          "parent_url": "https://conxa.pipedrive.com/persons/list/user/everyone?quickFilter=none"
        }
      ]
    },
    {
      "ts": 1779853420271,
      "frames": [
        {
          "url": "https://conxa.pipedrive.com/persons/list/user/everyone?quickFilter=none",
          "parent_url": null
        },
        {
          "url": "about:blank",
          "parent_url": "https://conxa.pipedrive.com/persons/list/user/everyone?quickFilter=none"
        },
        {
          "url": "about:blank",
          "parent_url": "https://conxa.pipedrive.com/persons/list/user/everyone?quickFilter=none"
        }
      ]
    },
    {
      "ts": 1779853421415,
      "frames": [
        {
          "url": "https://conxa.pipedrive.com/persons/list/user/everyone?quickFilter=none",
          "parent_url": null
        },
        {
          "url": "about:blank",
          "parent_url": "https://conxa.pipedrive.com/persons/list/user/everyone?quickFilter=none"
        },
        {
          "url": "about:blank",
          "parent_url": "https://conxa.pipedrive.com/persons/list/user/everyone?quickFilter=none"
        }
      ]
    },
    {
      "ts": 1779853423252,
      "frames": [
        {
          "url": "https://conxa.pipedrive.com/persons/list/user/everyone?quickFilter=none",
          "parent_url": null
        },
        {
          "url": "about:blank",
          "parent_url": "https://conxa.pipedrive.com/persons/list/user/everyone?quickFilter=none"
        },
        {
          "url": "about:blank",
          "parent_url": "https://conxa.pipedrive.com/persons/list/user/everyone?quickFilter=none"
        }
      ]
    },
    {
      "ts": 1779853424923,
      "frames": [
        {
          "url": "https://conxa.pipedrive.com/persons/list/user/everyone?quickFilter=none",
          "parent_url": null
        },
        {
          "url": "about:blank",
          "parent_url": "https://conxa.pipedrive.com/persons/list/user/everyone?quickFilter=none"
        },
        {
          "url": "about:blank",
          "parent_url": "https://conxa.pipedrive.com/persons/list/user/everyone?quickFilter=none"
        }
      ]
    },
    {
      "ts": 1779853426050,
      "frames": [
        {
          "url": "https://conxa.pipedrive.com/persons/list/user/everyone?quickFilter=none",
          "parent_url": null
        },
        {
          "url": "about:blank",
          "parent_url": "https://conxa.pipedrive.com/persons/list/user/everyone?quickFilter=none"
        },
        {
          "url": "about:blank",
          "parent_url": "https://conxa.pipedrive.com/persons/list/user/everyone?quickFilter=none"
        }
      ]
    },
    {
      "ts": 1779853427170,
      "frames": [
        {
          "url": "https://conxa.pipedrive.com/persons/list/user/everyone?quickFilter=none",
          "parent_url": null
        },
        {
          "url": "about:blank",
          "parent_url": "https://conxa.pipedrive.com/persons/list/user/everyone?quickFilter=none"
        },
        {
          "url": "about:blank",
          "parent_url": "https://conxa.pipedrive.com/persons/list/user/everyone?quickFilter=none"
        }
      ]
    },
    {
      "ts": 1779853428286,
      "frames": [
        {
          "url": "https://conxa.pipedrive.com/persons/list/user/everyone?quickFilter=none",
          "parent_url": null
        },
        {
          "url": "about:blank",
          "parent_url": "https://conxa.pipedrive.com/persons/list/user/everyone?quickFilter=none"
        },
        {
          "url": "about:blank",
          "parent_url": "https://conxa.pipedrive.com/persons/list/user/everyone?quickFilter=none"
        }
      ]
    },
    {
      "ts": 1779853429437,
      "frames": [
        {
          "url": "https://conxa.pipedrive.com/persons/list/user/everyone?quickFilter=none",
          "parent_url": null
        },
        {
          "url": "about:blank",
          "parent_url": "https://conxa.pipedrive.com/persons/list/user/everyone?quickFilter=none"
        },
        {
          "url": "about:blank",
          "parent_url": "https://conxa.pipedrive.com/persons/list/user/everyone?quickFilter=none"
        }
      ]
    }
  ]
}